encpng.py
encpng-0.2a0.dist-info/LICENSE
encpng-0.2a0.dist-info/METADATA
encpng-0.2a0.dist-info/WHEEL
encpng-0.2a0.dist-info/top_level.txt
encpng-0.2a0.dist-info/RECORD
