Metadata-Version: 2.1
Name: encpng
Version: 0.2a0
Summary: A steganographic library to encrypt files and text in PNG images
Home-page: https://github.com/tadaka9/encpng
Author: tadaka9
Author-email: trapdoorfunction@gmail.com
License: UNKNOWN
Keywords: steganography,cryptography,images
Platform: UNKNOWN
Classifier: Development Status :: 3 - Alpha
Classifier: Intended Audience :: Developers
Classifier: Topic :: Software Development :: Build Tools
Classifier: License :: OSI Approved :: MIT License
Classifier: Programming Language :: Python :: 3
Classifier: Programming Language :: Python :: 3.6
Classifier: Programming Language :: Python :: 3.7
Classifier: Programming Language :: Python :: 3.8
Classifier: Programming Language :: Python :: 3.9
Classifier: Programming Language :: Python :: 3 :: Only
Requires-Python: >=3.6, <4
Requires-Dist: Pillow
Requires-Dist: filetype
Requires-Dist: py-cpuinfo
Requires-Dist: pybase64
Requires-Dist: pycryptodomex
